tree_sitter_cairo/__init__.py
tree_sitter_cairo/typed_parser.py
tree_sitter_cairo-0.0.2.dist-info/METADATA
tree_sitter_cairo-0.0.2.dist-info/WHEEL
tree_sitter_cairo-0.0.2.dist-info/top_level.txt
tree_sitter_cairo-0.0.2.dist-info/RECORD
