Metadata-Version: 2.1
Name: tree-sitter-cairo
Version: 0.0.2
Summary: A tree-sitter based typed parser for the cairo language
Home-page: https://github.com/joranhonig/tree-sitter-cairo/
Author: Joran Honig
Author-email: joran.honig@gmail.com
Classifier: Programming Language :: Python :: 3
Classifier: Programming Language :: Python :: 3.7
Requires-Dist: tree-sitter-types
